<?xml version="1.0" encoding="utf-8" ?>

<language>
	<!-- values that should be customized: -->
	<word key="BrewClubName" value="Westman Alers" />
	<word key="SiteTitleFormat" value="Westman Alers - {0}" />
	
	
	<!-- values that probably don't need to be changed: -->
	<word key="Buy and Sell" value="Buy and Sell" />
	<word key="Contact" value="Contact" />
	<word key="Home" value="Home" />
	<word key="Login" value="Login" />
	<word key="Member Posts" value="Member Posts" />
	<word key="Recipes" value="Recipes" />
	<word key="Register" value="Register" />
	<word key="Toggle navigation" value="Toggle navigation" />
	<word key="Email" value="Email" />
	<word key="Password" value="Password" />
	<word key="Remember me" value="Remember me" />
	
</language>